{"2e04F1":"Assets\/uploads\/20221205-134555.jpg","d0E5C1":"Assets\/uploads\/login-bg-aachi.jpg","888C8B":"Assets\/uploads\/z9w6jcdtv7731.jpg","3C94AC":"Assets\/uploads\/Rizi\u00e8res-de-Ta-Pa-dans-le-delta-du-M\u00e9kong-Vietnam.jpg","1D3B67":"Assets\/uploads\/Screenshot_20221205-080909.jpg","43C810":"Assets\/uploads\/1724828115118.jpg","AEE3a9":"Assets\/uploads\/1724826535666.jpg","4dAD5d":"Assets\/uploads\/1724826535666.jpg","C31e26":"Assets\/uploads\/1724826535666.jpg","F02D0e":"Assets\/uploads\/1724826535666.jpg","e8A8bA":"Assets\/uploads\/1724826535591.jpg","3cAEAA":"Assets\/uploads\/1724826535666.jpg","92464E":"Assets\/uploads\/1724826535666.jpg","96148f":"Assets\/uploads\/1724828415392.jpg","7DE0F2":"Assets\/uploads\/1724828115169.jpg","a0f483":"Assets\/uploads\/1724828415259.jpg","0EE7A1":"Assets\/uploads\/1724828415519.jpg","EFdEB9":"Assets\/uploads\/trame.png","5361D8":"Assets\/uploads\/1724828281109.jpg","5a03F0":"Assets\/uploads\/1724828281175.jpg","9214e9":"Assets\/uploads\/1724828415519.jpg","8AB009":"Assets\/uploads\/1724826535591.jpg","E16966":"Assets\/uploads\/12c63f74554a47408f0ef9c5bbc50065.jpg"}